wood_wide_ai/__init__.py
wood_wide_ai/_base_client.py
wood_wide_ai/_client.py
wood_wide_ai/_compat.py
wood_wide_ai/_constants.py
wood_wide_ai/_exceptions.py
wood_wide_ai/_files.py
wood_wide_ai/_models.py
wood_wide_ai/_qs.py
wood_wide_ai/_resource.py
wood_wide_ai/_response.py
wood_wide_ai/_streaming.py
wood_wide_ai/_types.py
wood_wide_ai/_version.py
wood_wide_ai/py.typed
wood_wide_ai/_utils/__init__.py
wood_wide_ai/_utils/_compat.py
wood_wide_ai/_utils/_datetime_parse.py
wood_wide_ai/_utils/_logs.py
wood_wide_ai/_utils/_proxy.py
wood_wide_ai/_utils/_reflection.py
wood_wide_ai/_utils/_resources_proxy.py
wood_wide_ai/_utils/_streams.py
wood_wide_ai/_utils/_sync.py
wood_wide_ai/_utils/_transform.py
wood_wide_ai/_utils/_typing.py
wood_wide_ai/_utils/_utils.py
wood_wide_ai/lib/.keep
wood_wide_ai/resources/__init__.py
wood_wide_ai/resources/auth.py
wood_wide_ai/resources/api/__init__.py
wood_wide_ai/resources/api/api.py
wood_wide_ai/resources/api/datasets.py
wood_wide_ai/resources/api/models/__init__.py
wood_wide_ai/resources/api/models/anomaly.py
wood_wide_ai/resources/api/models/clustering.py
wood_wide_ai/resources/api/models/embedding.py
wood_wide_ai/resources/api/models/models.py
wood_wide_ai/resources/api/models/prediction.py
wood_wide_ai/types/__init__.py
wood_wide_ai/types/auth_retrieve_me_response.py
wood_wide_ai/types/api/__init__.py
wood_wide_ai/types/api/dataset_delete_params.py
wood_wide_ai/types/api/dataset_list_params.py
wood_wide_ai/types/api/dataset_list_response.py
wood_wide_ai/types/api/dataset_public.py
wood_wide_ai/types/api/dataset_retrieve_params.py
wood_wide_ai/types/api/dataset_upload_params.py
wood_wide_ai/types/api/model_list_response.py
wood_wide_ai/types/api/model_public.py
wood_wide_ai/types/api/model_retrieve_params.py
wood_wide_ai/types/api/schema.py
wood_wide_ai/types/api/models/__init__.py
wood_wide_ai/types/api/models/anomaly_infer_params.py
wood_wide_ai/types/api/models/anomaly_train_params.py
wood_wide_ai-0.1.0.dist-info/METADATA
wood_wide_ai-0.1.0.dist-info/WHEEL
wood_wide_ai-0.1.0.dist-info/licenses/LICENSE
wood_wide_ai-0.1.0.dist-info/RECORD
